{
    "version": "29.30.0",
    "description": "All the official themes for Oh-My-Posh",
    "homepage": "https://ohmyposh.dev",
    "license": "MIT",
    "notes": "Refer to 'https://ohmyposh.dev/docs/installation/prompt' for shell specific configurations.",
    "url": "https://github.com/JanDeDobbeleer/oh-my-posh/releases/download/v29.30.0/themes.zip",
    "hash": "a7783b04b807ba7eb708dbd6eebd91c85b542153329d86e778d42e6c6dad22a8",
    "depends": "oh-my-posh",
    "env_set": {
        "POSH_THEMES_PATH": "$dir"
    },
    "checkver": {
        "github": "https://github.com/JanDeDobbeleer/oh-my-posh"
    },
    "autoupdate": {
        "url": "https://github.com/JanDeDobbeleer/oh-my-posh/releases/download/v$version/themes.zip",
        "hash": {
            "url": "$url.sha256"
        }
    }
}
