{
    "version": "26.10.1",
    "description": "All the official themes for Oh-My-Posh",
    "homepage": "https://ohmyposh.dev",
    "license": "MIT",
    "notes": "Refer to 'https://ohmyposh.dev/docs/installation/prompt' for shell specific configurations.",
    "url": "https://github.com/JanDeDobbeleer/oh-my-posh/releases/download/v26.10.1/themes.zip",
    "hash": "e2294c4be677514edf45375aa59d6426a5f6e7789f5cd74a36ac2d2d9e4ada38",
    "depends": "oh-my-posh",
    "env_set": {
        "POSH_THEMES_PATH": "$dir"
    },
    "checkver": {
        "github": "https://github.com/JanDeDobbeleer/oh-my-posh"
    },
    "autoupdate": {
        "url": "https://github.com/JanDeDobbeleer/oh-my-posh/releases/download/v$version/themes.zip",
        "hash": {
            "url": "$url.sha256"
        }
    }
}
