{
    "version": "24.1.0",
    "description": "All the official themes for Oh-My-Posh",
    "homepage": "https://ohmyposh.dev",
    "license": "MIT",
    "notes": "Refer to 'https://ohmyposh.dev/docs/installation/prompt' for shell specific configurations.",
    "url": "https://github.com/JanDeDobbeleer/oh-my-posh/releases/download/v24.1.0/themes.zip",
    "hash": "26b6a082429efa661e8cfb638f1f354e3b0915785fa5948e14ad5f5e7e66c8ed",
    "depends": "oh-my-posh",
    "env_set": {
        "POSH_THEMES_PATH": "$dir"
    },
    "checkver": {
        "github": "https://github.com/JanDeDobbeleer/oh-my-posh"
    },
    "autoupdate": {
        "url": "https://github.com/JanDeDobbeleer/oh-my-posh/releases/download/v$version/themes.zip",
        "hash": {
            "url": "$url.sha256"
        }
    }
}
